{
	"schemaVersion": 1,
	"id": "anemos",
	"version": "${version}",
	"name": "Anemos",
	"description": "Unleash the true gamma and conquer the darkness!",
	"authors": [
		"PrinceParshia"
	],
	"contact": {
		"homepage": "https://modrinth.com/mods/anemos",
		"issues": "https://github.com/PrinceParshia/Anemos/issues"
	},
	"license": "All Rights Reserved",
	"icon": "anemos.png",
	"environment": "client",
	"entrypoints": {
		"client": [
			"princ.anemos.client.Anemos"
		]
	},
	"mixins": [
		"anemos.mixins.json"
	],
	"accessWidener": "anemos.accesswidener",
	"depends": {
		"fabricloader": ">=0.16.0",
		"minecraft": ">=1.21.2",
		"java": ">=21",
		"fabric-api": "*",
		"fzzy_config": "*"
	}
}